<?xml version="1.0" encoding="UTF-8" standalone="no"?><timetable importtype="database" options="export:idprefix:MyApp"><periods columns="period,name,short,starttime,endtime" options="canadd,export:silent"><period endtime="8:00" name="1" period="1" short="1" starttime="7:00"/><period endtime="9:00" name="2" period="2" short="2" starttime="8:00"/><period endtime="10:00" name="3" period="3" short="3" starttime="9:00"/><period endtime="11:00" name="4" period="4" short="4" starttime="10:00"/><period endtime="12:00" name="5" period="5" short="5" starttime="11:00"/><period endtime="13:00" name="6" period="6" short="6" starttime="12:00"/><period endtime="14:00" name="7" period="7" short="7" starttime="13:00"/><period endtime="15:00" name="8" period="8" short="8" starttime="14:00"/><period endtime="16:00" name="9" period="9" short="9" starttime="15:00"/><period endtime="17:00" name="10" period="10" short="10" starttime="16:00"/><period endtime="18:00" name="11" period="11" short="11" starttime="17:00"/><period endtime="19:00" name="12" period="12" short="12" starttime="18:00"/><period endtime="20:00" name="13" period="13" short="13" starttime="19:00"/><period endtime="21:00" name="14" period="14" short="14" starttime="20:00"/></periods><daysdefs columns="id,days,name,short" options="canadd,export:silent"><daysdef days="100000,010000,001000,000100,000010,000001" id="1" name="Cualquier día" short="X"/><daysdef days="111111" id="2" name="Cada día" short="E"/><daysdef days="100000" id="3" name="Lunes" short="Lu"/><daysdef days="010000" id="4" name="Martes" short="Ma"/><daysdef days="001000" id="5" name="Miercoles" short="Mi"/><daysdef days="000100" id="6" name="Jueves" short="Ju"/><daysdef days="000010" id="7" name="Viernes" short="Vi"/><daysdef days="000001" id="8" name="Sabado" short="Sá"/></daysdefs><weeksdefs columns="id,weeks,name,short" options="canadd,export:silent"><weeksdef id="1" name="Todas las semanas" short="Todas" weeks="1"/></weeksdefs><termsdefs columns="id,terms,name,short" options="canadd,export:silent"><termsdef id="2" name="Todas el año" short="Año" terms="1"/></termsdefs><teachers columns="id,name,short,color,email,timeoff" options="canadd,export:silent"><teacher color="#00FF00" email="eoocampo.datic@utez.edu.mx" id="1" name="Erick Ricardo Ocampo Gómez" short="EO" timeoff=".111110011111111,.111110011111111,.111110011111111,.111110011111111,.111110011111111,.111110011111111"/></teachers></timetable>